cmsisdsp_basic.cpython-313-aarch64-linux-gnu.so
cmsisdsp_bayes.cpython-313-aarch64-linux-gnu.so
cmsisdsp_complexf.cpython-313-aarch64-linux-gnu.so
cmsisdsp_controller.cpython-313-aarch64-linux-gnu.so
cmsisdsp_distance.cpython-313-aarch64-linux-gnu.so
cmsisdsp_fastmath.cpython-313-aarch64-linux-gnu.so
cmsisdsp_filtering.cpython-313-aarch64-linux-gnu.so
cmsisdsp_interpolation.cpython-313-aarch64-linux-gnu.so
cmsisdsp_matrix.cpython-313-aarch64-linux-gnu.so
cmsisdsp_quaternion.cpython-313-aarch64-linux-gnu.so
cmsisdsp_statistics.cpython-313-aarch64-linux-gnu.so
cmsisdsp_support.cpython-313-aarch64-linux-gnu.so
cmsisdsp_svm.cpython-313-aarch64-linux-gnu.so
cmsisdsp_transform.cpython-313-aarch64-linux-gnu.so
cmsisdsp_window.cpython-313-aarch64-linux-gnu.so
cmsisdsp/__init__.py
cmsisdsp/datatype.py
cmsisdsp/demo.py
cmsisdsp/fixedpoint.py
cmsisdsp/mfcc.py
cmsisdsp/version.py
cmsisdsp-1.10.2.dist-info/METADATA
cmsisdsp-1.10.2.dist-info/WHEEL
cmsisdsp-1.10.2.dist-info/top_level.txt
cmsisdsp-1.10.2.dist-info/RECORD
cmsisdsp-1.10.2.dist-info/licenses/LICENSE
