Metadata-Version: 2.4
Name: cmsisdsp
Version: 1.10.2
Summary: CMSIS-DSP Python API
Home-page: https://github.com/ARM-software/CMSIS-DSP
Author: Copyright (C) 2010-2025 ARM Limited or its affiliates. All rights reserved.
Author-email: christophe.favergeon@arm.com
License: License :: OSI Approved :: Apache Software License
Project-URL: Bug Reports, https://github.com/ARM-software/CMSIS-DSP/issues
Project-URL: Source, https://github.com/ARM-software/CMSIS-DSP
Keywords: development,dsp,cmsis,cmsis-dsp,Arm,signal processing,maths,ml,cortex-m,cortex-a
Platform: any
Classifier: Programming Language :: Python :: 3
Classifier: Programming Language :: Python :: Implementation :: CPython
Classifier: Programming Language :: C
Classifier: License :: OSI Approved :: Apache Software License
Classifier: Operating System :: OS Independent
Classifier: Development Status :: 5 - Production/Stable
Classifier: Topic :: Software Development :: Embedded Systems
Classifier: Topic :: Scientific/Engineering :: Mathematics
Classifier: Environment :: Console
Classifier: Intended Audience :: Developers
Requires-Python: >=3.9
License-File: LICENSE
Requires-Dist: numpy>=1.23.5
Dynamic: author
Dynamic: author-email
Dynamic: classifier
Dynamic: description
Dynamic: description-content-type
Dynamic: home-page
Dynamic: keywords
Dynamic: license
Dynamic: license-file
Dynamic: platform
Dynamic: project-url
Dynamic: requires-dist
Dynamic: requires-python
Dynamic: summary
